gemini_batch_processor/__init__.py
gemini_batch_processor/gemini_bot.py
gemini_batch_processor-1.0.1.dist-info/LICENSE
gemini_batch_processor-1.0.1.dist-info/METADATA
gemini_batch_processor-1.0.1.dist-info/WHEEL
gemini_batch_processor-1.0.1.dist-info/top_level.txt
gemini_batch_processor-1.0.1.dist-info/RECORD
