Metadata-Version: 2.1
Name: gemini_batch_processor
Version: 1.0.1
Summary: A Python module to process bulk data using Google's generative AI (Gemini).
Home-page: https://github.com/Yukendiran2002/GeminiDataProcessor
Author: Yukendiran
Author-email: yukendiranjayachandiran@gmail.com
Classifier: Programming Language :: Python :: 3
Classifier: License :: OSI Approved :: MIT License
Classifier: Operating System :: OS Independent
Requires-Python: >=3.8
License-File: LICENSE
Requires-Dist: pandas
Requires-Dist: tqdm
Requires-Dist: google-generativeai
Requires-Dist: nest-asyncio
Requires-Dist: pytz
